persian_phonemizer/Phonemizer.py
persian_phonemizer/__init__.py
persian_phonemizer/dicts.py
persian_phonemizer/utils.py
persian_phonemizer/data/cfg
persian_phonemizer/data/moen_parsed.db
persian_phonemizer/data/nlp_data
persian_phonemizer-0.4.0.dist-info/LICENSE
persian_phonemizer-0.4.0.dist-info/METADATA
persian_phonemizer-0.4.0.dist-info/WHEEL
persian_phonemizer-0.4.0.dist-info/top_level.txt
persian_phonemizer-0.4.0.dist-info/RECORD
