Metadata-Version: 2.1
Name: persian-phonemizer
Version: 0.4.0
Summary: A tool for translating Persian text to IPA (International Phonetic Alphabet)A small example package
Home-page: https://github.com/de-mh/persian_phonemizer
Author: Mohamadhosein Dehghani
Author-email: demh1377@gmail.com
Classifier: Programming Language :: Python :: 3
Classifier: License :: OSI Approved :: MIT License
Classifier: Operating System :: OS Independent
Requires-Python: >=3.6
License-File: LICENSE
Requires-Dist: spacy (>=3.3)
Requires-Dist: g2p-fa
Requires-Dist: hazm
